<?xml version="1.0" encoding="utf-8"?>
<items>
<item><quote><value>
                I hear and i forget.</value><value> I see and i remember.</value><value> I do and i understand.
            </value></quote><author>
                Confucious
            </author></item>
<item><quote><value>
                    Feeling gratitude and not</value><value> expressing it is like wrapping</value><value> a present and not giving it.
                </value></quote><author>
                    William Arthur Ward
                </author></item>
<item><quote><value>
                    Our greatest glory is not in never falling</value><value> but in rising every time we fall.
                </value></quote><author>
                    Confucious
                </author></item>
<item><quote><value>
                    The secret of getting ahead</value><value>is getting started.
                </value></quote><author>
                    Mark Twain
                </author></item>
<item><quote><value>
                    Believe you can  </value><value> and you're halfway there.
                </value></quote><author>
                    Theodore Roosevelt
                </author></item>
<item><quote><value>
                    Resentment is like drinking Poison and  </value><value>waiting for your enemies to die.
                </value></quote><author>
                    Nelson Mandela
                </author></item>
<item><quote><value>
                    Silence is a true friend  </value><value> who never betrays.
                </value></quote><author>
                    Confucius
                </author></item>
<item><quote><value>
                    The best way to find yourself is to  </value><value> lose yourself in the service of others.
                </value></quote><author>
                    Mahatma Gandhi
                </author></item>
<item><quote><value>
                    Never succumb to the </value><value>temptation of bitterness.
                </value></quote><author>
                    Martin Luther King Jnr
                </author></item>
<item><quote><value>
                    The journey of a thousand miles  </value><value>begins with one step.
                </value></quote><author>
                    Lao Tzu
                </author></item>
<item><quote><value>
                    It is health that is real wealth and  </value><value>not pieces of gold and silver.
                </value></quote><author>
                    Mahatma Gandhi
                </author></item>
<item><quote><value>
                    Yesterday is not ours to recover  </value><value>but tomorrow is ours to win or lose.
                </value></quote><author>
                    Lyndon B Johnson
                </author></item>
<item><quote><value>
                    It's not what happens to you  </value><value>but how you react to it that matters .
                </value></quote><author>
                    Epictetus
                </author></item>
<item><quote><value>
                    Beware of what you become  </value><value>in pursuit of what you want.
                </value></quote><author>
                    Jim Rohn
                </author></item>
<item><quote><value>
                    The best revenge  </value><value>is massive success.
                </value></quote><author>
                    Frank Sinatra
                </author></item>
<item><quote><value>
                    Do not take life too seriously </value><value>You will never get out of it alive.
                </value></quote><author>
                    Elbert Hubbard
                </author></item>
<item><quote><value>
                    Don't judge each day by the harvest you reap  </value><value>but by the seeds that yiu plant.
                </value></quote><author>
                    Robert Loius Stevenson
                </author></item>
<item><quote><value>
                    Your attitude and not your aptitude  </value><value>will determine your altitude
                </value></quote><author>
                    Zig Ziglar
                </author></item>
<item><quote><value>
                    Imagination is more important  </value><value>than knowledge.
                </value></quote><author>
                    Albert Einstein
                </author></item>
</items>